LICENSE
README.md
setup.py
steam_jack/__init__.py
steam_jack.egg-info/PKG-INFO
steam_jack.egg-info/SOURCES.txt
steam_jack.egg-info/dependency_links.txt
steam_jack.egg-info/requires.txt
steam_jack.egg-info/top_level.txt
steam_jack/Communicator/Communicator.py
steam_jack/Communicator/Communicator_Constants.py
steam_jack/DeviceLibrary/Emlid_navio.py
steam_jack/Logger/Logger.py
steam_jack/Communicator/Communicator.py
steam_jack/Communicator/Communicator_Constants.py
steam_jack/Communicator/__init__.py
steam_jack/DeviceLibrary/Emlid_navio.py
steam_jack/DeviceLibrary/__init__.py
steam_jack/Logger/Logger.py
steam_jack/Logger/__init__.py