Metadata-Version: 2.1
Name: steam-jack
Version: 0.0.5
Summary: Steam-jack development interface
Home-page: https://github.com/BertVanAcker/steam-jack.git
Author: Bert Van Acker
Author-email: bva.bmkr@gmail.com
License: LICENSE.txt
Platform: UNKNOWN
License-File: LICENSE
